sarajas/_API.py
sarajas/__init__.py
sarajas/__main__.py
sarajas/meta/_API.py
sarajas/meta/__init__.py
sarajas/meta/__main__.py
sarajas/meta/constructor.py
sarajas/meta/texttools.py
sarajas/meta/boot/__init__.py
sarajas/meta/boot/core.py
sarajas-0.0.4.dist-info/LICENSE
sarajas-0.0.4.dist-info/METADATA
sarajas-0.0.4.dist-info/WHEEL
sarajas-0.0.4.dist-info/entry_points.txt
sarajas-0.0.4.dist-info/top_level.txt
sarajas-0.0.4.dist-info/RECORD
