Metadata-Version: 2.1
Name: sarajas
Version: 0.0.4
Summary: Toolkit for Python development, especially packaging 
Author: Limespy
Project-URL: Homepage, https://github.com/Limespy/sarajas
Project-URL: Changelog, https://github.com/Limespy/sarajas/blob/main/README.md#Changelog
Project-URL: Issue Tracker, https://github.com/Limespy/sarajas/issues
Classifier: Development Status :: 2 - Pre-Alpha
Classifier: License :: OSI Approved :: MIT License
Classifier: Operating System :: Unix
Classifier: Operating System :: POSIX
Classifier: Operating System :: Microsoft :: Windows
Classifier: Programming Language :: Python :: 3
Classifier: Programming Language :: Python :: 3 :: Only
Classifier: Programming Language :: Python :: 3.10
Classifier: Programming Language :: Python :: 3.11
Classifier: Programming Language :: Python :: 3.12
Classifier: Programming Language :: Python :: 3.13
Requires-Python: >=3.10
License-File: LICENSE
Requires-Dist: limedev >=0.6.0
Requires-Dist: pyyaml >=6.0.1
Provides-Extra: build
Requires-Dist: limedev[package] >=0.6.0 ; extra == 'build'
Provides-Extra: dev
Requires-Dist: limedev[package,readme,test] >=0.6.0 ; extra == 'dev'
Requires-Dist: tox >=4.5.1 ; extra == 'dev'
